{
  "data": [
    {
      "id": 0,
      "name": "000 template",
      "filename": "000_template.md"
    },
    {
      "id": 1,
      "name": "001 Notation",
      "filename": "001_notation.md"
    },
    {
      "id": 2,
      "name": "002 Descripci贸n",
      "filename": "002_descripci贸n.md"
    },
    {
      "id": 3,
      "name": "003 Promises",
      "filename": "003_promises-js.md"
    },
    {
      "id": 4,
      "name": "000 Template",
      "filename": "000_template.md"
    },
    {
      "id": 5,
      "name": "001 Notation",
      "filename": "001_notation.md"
    },
    {
      "id": 6,
      "name": "002 Descripci贸n",
      "filename": "002_descripci贸n.md"
    },
    {
      "id": 7,
      "name": "003 Promises",
      "filename": "003_promises-js.md"
    }
  ]
}